reegis/__init__.py
reegis/bmwi.py
reegis/coastdat.py
reegis/commodity_sources.py
reegis/config.py
reegis/demand_elec.py
reegis/demand_heat.py
reegis/dictionary.ini
reegis/energy_balance.py
reegis/entsoe.py
reegis/feedin.py
reegis/geometries.py
reegis/inhabitants.py
reegis/mobility.ini
reegis/mobility.py
reegis/oedb.py
reegis/openego.py
reegis/opsd.py
reegis/powerplants.py
reegis/reegis.ini
reegis/solar.ini
reegis/storages.py
reegis/tools.py
reegis/wind.ini
reegis/data/geometries/coastdatgrid_centroid.csv
reegis/data/geometries/coastdatgrid_polygons.csv
reegis/data/geometries/de_grid_please_check.csv
reegis/data/geometries/federalstates_centroid.csv
reegis/data/geometries/federalstates_extended_polygon.geojson
reegis/data/geometries/federalstates_polygon.csv
reegis/data/geometries/germany_awz_polygon.geojson
reegis/data/geometries/germany_polygon.geojson
reegis/data/geometries/intersection_region_coastdatgrid.csv
reegis/data/geometries/intersection_state_coastdatgrid.csv
reegis/data/geometries/offshore_regions.geojson
reegis/data/geometries/overlap_region_polygon.csv
reegis/data/geometries/postcode_polygons.csv
reegis/data/geometries/powerlines_labels_de21.csv
reegis/data/geometries/powerlines_lines_de21.csv
reegis/data/geometries/region_labels_de21.csv
reegis/data/geometries/region_polygons_de21.geojson
reegis/data/geometries/region_polygons_de21_vg.csv
reegis/data/geometries/region_polygons_de21_wiese.csv
reegis/data/geometries/vg1000_geodata.geojson
reegis/data/geometries/windzones_germany.geojson
reegis/data/static/energy_balance_federal_states.csv
reegis/data/static/energy_balance_header.csv
reegis/data/static/energy_balance_header_germany.csv
reegis/data/static/energybalance_DE_2012_to_2014.csv
reegis/data/static/energybalance_conversion_2012_to_2014.csv
reegis/data/static/energybalance_states_2012_to_2014.csv
reegis/data/static/oedb.demand.ego_dp_loadarea_v0.2.10_WGS84_170721.csv
reegis/data/static/oedb.demand.ego_dp_loadarea_v0.2.10_WGS84_170721_readme.txt
reegis-0.2.1.dist-info/LICENSE
reegis-0.2.1.dist-info/METADATA
reegis-0.2.1.dist-info/WHEEL
reegis-0.2.1.dist-info/top_level.txt
reegis-0.2.1.dist-info/RECORD
