Metadata-Version: 2.1
Name: reegis
Version: 0.2.1
Summary: Open geospatial data model
Home-page: https://github.com/reegis/reegis
Author: Uwe Krien
Author-email: krien@uni-bremen.de
License: MIT
Platform: UNKNOWN
Requires-Python: >=3.6
Requires-Dist: pandas
Requires-Dist: demandlib
Requires-Dist: tables
Requires-Dist: shapely
Requires-Dist: pvlib
Requires-Dist: geopandas
Requires-Dist: requests
Requires-Dist: numpy
Requires-Dist: workalendar
Requires-Dist: pyproj
Requires-Dist: pytz
Requires-Dist: windpowerlib
Requires-Dist: python-dateutil
Requires-Dist: Rtree
Requires-Dist: xlrd
Requires-Dist: xlwt
Provides-Extra: dev
Requires-Dist: nose ; extra == 'dev'
Requires-Dist: cython ; extra == 'dev'
Requires-Dist: sphinx ; extra == 'dev'
Requires-Dist: sphinx-rtd-theme ; extra == 'dev'
Requires-Dist: matplotlib ; extra == 'dev'
Requires-Dist: descartes ; extra == 'dev'
Requires-Dist: request ; extra == 'dev'
